Workbook

Sheet Stock y Compras
A1: RUBRO | B1: BIEN | C1: ORDEN DE COMPRA | D1: CATALOGO | E1: RENGLÓN | F1: CANTIDAD COMPRADA | G1: PRECIO UNITARIO | H1: PRECIO TOTAL | I1: BIENES EN STOCK | J1: SALDO EN $
A2: INSUMOS AIRES | B2: EQUIPO SPLIT DE 4500 FRIGORÍAS - TIPO DE CLIMATIZACIÓNFRIO/CALOR - EFICIENCIA ENERGÉTICA DE CLASE C O MAYOR | C2: 81-0080-OC24 | D2: 4.3.7-1367.320 | E2: 1 | F2: 13 | G2: 907100 | H2: =F2*G2 -> 11792300 | I2: =F2-SUMIFS(Pedidos!G:G, Pedidos!D:D, C2, Pedidos!E:E, E2, Pedidos!F:F, B2) -> 8 | J2: =I2*G2 -> 7256800
A3: INSUMOS AIRES | B3: EQUIPO SPLIT DE 6000 FRIGORÍAS - TIPO DE CLIMATIZACIÓN FRIO/CALOR - EFICIENCIA ENERGÉTICA DE CLASE C O MAYOR EN CALEFACCIÓN Y A EN REFRIGERACIÓN - NO CONVERTER | C3: 81-0081-OC24 | D3: 4.3.7-1367.330 | E3: 2 | F3: 11 | G3: 1413000 | H3: =F3*G3 -> 15543000 | I3: =F3-SUMIFS(Pedidos!G:G, Pedidos!D:D, C3, Pedidos!E:E, E3, Pedidos!F:F, B3) -> 4 | J3: =I3*G3 -> 5652000
A4: INSUMOS AIRES | B4: ROLLO DE 15 METROS CAÑO DE COBRE DE 5/8 | C4: 81-0082-OC24 | D4: 2.9.6-5591.3 | E4: 3 | F4: 4 | G4: 201000 | H4: =F4*G4 -> 804000 | I4: =F4-SUMIFS(Pedidos!G:G, Pedidos!D:D, C4, Pedidos!E:E, E4, Pedidos!F:F, B4) -> 2 | J4: =I4*G4 -> 402000
A5: INSUMOS AIRES | B5: ROLLO DE 15 METROS CAÑO DE COBRE DE 3/8 | C5: 81-0082-OC24 | D5: 2.9.6-5591.4 | E5: 4 | F5: 4 | G5: 112000 | H5: =F5*G5 -> 448000 | I5: =F5-SUMIFS(Pedidos!G:G, Pedidos!D:D, C5, Pedidos!E:E, E5, Pedidos!F:F, B5) -> 4 | J5: =I5*G5 -> 448000
A6: INSUMOS AIRES | B6: ROLLO DE 15 METROS CAÑO DE COBRE DE 1/2 | C6: 81-0082-OC24 | D6: 2.9.6-5591.5 | E6: 5 | F6: 5 | G6: 157000 | H6: =F6*G6 -> 785000 | I6: =F6-SUMIFS(Pedidos!G:G, Pedidos!D:D, C6, Pedidos!E:E, E6, Pedidos!F:F, B6) -> 2 | J6: =I6*G6 -> 314000
A7: INSUMOS AIRES | B7: ROLLO DE 15 METROS CAÑO DE COBRE DE 1/4 | C7: 81-0082-OC24 | D7: 2.9.6-5591.6 | E7: 6 | F7: 5 | G7: 73000 | H7: =F7*G7 -> 365000 | I7: =F7-SUMIFS(Pedidos!G:G, Pedidos!D:D, C7, Pedidos!E:E, E7, Pedidos!F:F, B7) -> 0 | J7: =I7*G7 -> 0
A8: INSUMOS AIRES | B8: ROLLO DE 2 METROS DE TIRA DE AISLACIÓN TÉRMICA PARA CAÑOS DE 5/8 | C8: 81-0082-OC24 | D8: 2.9.6-1712.305 | E8: 7 | F8: 33 | G8: 2990 | H8: =F8*G8 -> 98670 | I8: =F8-SUMIFS(Pedidos!G:G, Pedidos!D:D, C8, Pedidos!E:E, E8, Pedidos!F:F, B8) -> 17 | J8: =I8*G8 -> 50830
A9: INSUMOS AIRES | B9: ROLLO DE 2 METROS DE TIRA DE AISLACIÓN TÉRMICA PARA CAÑOS DE 3/8 | C9: 81-0082-OC24 | D9: 2.9.6-1712.306 | E9: 8 | F9: 33 | G9: 2300 | H9: =F9*G9 -> 75900 | I9: =F9-SUMIFS(Pedidos!G:G, Pedidos!D:D, C9, Pedidos!E:E, E9, Pedidos!F:F, B9) -> 24 | J9: =I9*G9 -> 55200
A10: INSUMOS AIRES | B10: ROLLO DE 2 METROS DE TIRA DE AISLACIÓN TÉRMICA PARA CAÑOS DE 1/2 | C10: 81-0082-OC24 | D10: 2.9.6-1712.307 | E10: 9 | F10: 42 | G10: 2590 | H10: =F10*G10 -> 108780 | I10: =F10-SUMIFS(Pedidos!G:G, Pedidos!D:D, C10, Pedidos!E:E, E10, Pedidos!F:F, B10) -> 22 | J10: =I10*G10 -> 56980
A11: INSUMOS AIRES | B11: ROLLO DE 2 METROS DE TIRA DE AISLACIÓN TÉRMICA PARA CAÑOS DE 1/4 | C11: 81-0082-OC24 | D11: 2.9.6-1712.308 | E11: 10 | F11: 42 | G11: 1630 | H11: =F11*G11 -> 68460 | I11: =F11-SUMIFS(Pedidos!G:G, Pedidos!D:D, C11, Pedidos!E:E, E11, Pedidos!F:F, B11) -> 13 | J11: =I11*G11 -> 21190
A12: INSUMOS AIRES | B12: CINTA DE PVC PARA REFRIGERACIÓN, SIN ADHESIVO – ROLLO DE 20 METROS | C12: 81-0082-OC24 | D12: 2.9.9-3027.9 | E12: 11 | F12: 24 | G12: 4000 | H12: =F12*G12 -> 96000 | I12: =F12-SUMIFS(Pedidos!G:G, Pedidos!D:D, C12, Pedidos!E:E, E12, Pedidos!F:F, B12) -> 5 | J12: =I12*G12 -> 20000
A13: INSUMOS AIRES | B13: MENSULAS PARA AIRE ACONDICIONADO DE 4500 A 6000 FRIGORIAS, 50X50 APROXIMADAMENTE | C13: 81-0082-OC24 | D13: 2.9.6-1376.235 | E13: 13 | F13: 24 | G13: 19200 | H13: =F13*G13 -> 460800 | I13: =F13-SUMIFS(Pedidos!G:G, Pedidos!D:D, C13, Pedidos!E:E, E13, Pedidos!F:F, B13) -> 21 | J13: =I13*G13 -> 403200
... A15: INSUMOS AIRES | B15: GARRAFA REFRIGERANTE R22 | C15: 81-0082-OC24 | D15: 2.5.6-6856.1 | E15: 15 | F15: 6 | G15: 440235 | H15: =F15*G15 -> 2641410 | I15: =F15-SUMIFS(Pedidos!G:G, Pedidos!D:D, C15, Pedidos!E:E, E15, Pedidos!F:F, B15) -> 5 | J15: =I15*G15 -> 2201175
A16: INSUMOS AIRES | B16: MANGUERA CRISTAL PARA DESAGÜE DE 5/8" – ROLLO DE 50 METROS (PRECIO POR METRO) | C16: 81-0082-OC24 | D16: 2.9.9-9053.30 | E16: 16 | F16: 150 | G16: =62000/50 -> 1240 | H16: =F16*G16 -> 186000 | I16: =F16-SUMIFS(Pedidos!G:G, Pedidos!D:D, C16, Pedidos!E:E, E16, Pedidos!F:F, B16) -> 125 | J16: =I16*G16 -> 155000
A17: INSUMOS AIRES | B17: TACO DE GOMA, AMORTIGUADOR ANTIVIBRACIÓN – BOLSA X 4 UNIDADES | C17: 81-0082-OC24 | D17: 2.9.6-1712.93 | E17: 17 | F17: 24 | G17: 2850 | H17: =F17*G17 -> 68400 | I17: =F17-SUMIFS(Pedidos!G:G, Pedidos!D:D, C17, Pedidos!E:E, E17, Pedidos!F:F, B17) -> 13 | J17: =I17*G17 -> 37050
A18: INSUMOS AIRES | B18: CAJA DE 200 TARUGOS MULTIPROPÓSITOS DE 8MM | C18: 81-0082-OC24 | D18: 2.5.8-819.9 | E18: 18 | F18: =7*200 -> 1400 | G18: =6400/200 -> 32 | H18: =F18*G18 -> 44800 | I18: =F18-SUMIFS(Pedidos!G:G, Pedidos!D:D, C18, Pedidos!E:E, E18, Pedidos!F:F, B18) -> 1160 | J18: =I18*G18 -> 37120
A19: INSUMOS AIRES | B19: CAJA DE 200 TARUGOS MULTIPROPÓSITOS DE 10MM | C19: 81-0082-OC24 | D19: 2.5.8-819.9 | E19: 19 | F19: =7*200 -> 1400 | G19: =13500/200 -> 67.5 | H19: =F19*G19 -> 94500 | I19: =F19-SUMIFS(Pedidos!G:G, Pedidos!D:D, C19, Pedidos!E:E, E19, Pedidos!F:F, B19) -> 1224 | J19: =I19*G19 -> 82620
A20: INSUMOS AIRES | B20: CAJA DE 200 TORNILLOS TIRAFONDO PARA TARUGO DE 10MM - PRECIO POR UNIDAD | C20: 81-0082-OC24 | D20: 2.7.9-643.112 | E20: 20 | F20: 1400 | G20: =23350/200 -> 116.75 | H20: =F20*G20 -> 163450 | I20: =F20-SUMIFS(Pedidos!G:G, Pedidos!D:D, C20, Pedidos!E:E, E20, Pedidos!F:F, B20) -> 1224 | J20: =I20*G20 -> 142902
A21: INSUMOS AIRES | B21: CAJA DE 200 TORNILLOS TIRAFONDO PARA TARUGO DE 8MM | C21: 81-0082-OC24 | D21: 2.7.9-643.25 | E21: 21 | F21: 1400 | G21: =15400/200 -> 77 | H21: =F21*G21 -> 107800 | I21: =F21-SUMIFS(Pedidos!G:G, Pedidos!D:D, C21, Pedidos!E:E, E21, Pedidos!F:F, B21) -> 1160 | J21: =I21*G21 -> 89320
A22: INSUMOS AIRES | B22: CAJA DE 200 ARANDELAS PLANAS PARA TARUGOS DE 10MM | C22: 81-0082-OC24 | D22: 2.7.9-1600.44 | E22: 22 | F22: =7*200 -> 1400 | G22: =8900/200 -> 44.5 | H22: =F22*G22 -> 62300 | I22: =F22-SUMIFS(Pedidos!G:G, Pedidos!D:D, C22, Pedidos!E:E, E22, Pedidos!F:F, B22) -> 1224 | J22: =I22*G22 -> 54468
A23: INSUMOS AIRES | B23: CAJA DE 200 ARANDELAS PLANAS PARA TARUGOS DE 8MM | C23: 81-0082-OC24 | D23: 2.7.9-1600.35 | E23: 23 | F23: =7*200 -> 1400 | G23: =6000/200 -> 30 | H23: =F23*G23 -> 42000 | I23: =F23-SUMIFS(Pedidos!G:G, Pedidos!D:D, C23, Pedidos!E:E, E23, Pedidos!F:F, B23) -> 1160 | J23: =I23*G23 -> 34800
A24: PLOMERIA | B24: ADHESIVO - CEMENTO DE CONTACTO; TIPO: DE CONTACTO, PRESENTACION: ENVASE X 1 L | C24: 81-0054-OC24 | D24: 2.5.9-6887.43 | E24: 19 | F24: 10 | G24: 10500 | H24: =F24*G24 -> 105000 | I24: =F24-SUMIFS(Pedidos!G:G, Pedidos!D:D, C24, Pedidos!E:E, E24, Pedidos!F:F, B24) -> 6 | J24: =I24*G24 -> 63000
A25: PLOMERIA | B25: ADHESIVO COLA CARPINTERO BLANCO | C25: EXISTENCIA PREV. 1 | E25: S/N | F25: 1 | G25: 73 | H25: =F25*G25 -> 73 | I25: =F25-SUMIFS(Pedidos!G:G, Pedidos!D:D, C25, Pedidos!E:E, E25, Pedidos!F:F, B25) -> 1 | J25: =I25*G25 -> 73
A26: PLOMERIA | B26: ARANDELA PLASTICA 1/2" | C26: EXISTENCIA PREV. 1 | D26: 2.5.8-6723.1 | E26: S/N | F26: 27 | G26: 1.2 | H26: =F26*G26 -> 32.4 | I26: =F26-SUMIFS(Pedidos!G:G, Pedidos!D:D, C26, Pedidos!E:E, E26, Pedidos!F:F, B26) -> 27 | J26: =I26*G26 -> 32.4
A27: PLOMERIA | B27: ARANDELA PLASTICA 3/4" | C27: EXISTENCIA PREV. 1 | D27: 2.5.8-6723.2 | E27: S/N | F27: 9 | G27: 0.5 | H27: =F27*G27 -> 4.5 | I27: =F27-SUMIFS(Pedidos!G:G, Pedidos!D:D, C27, Pedidos!E:E, E27, Pedidos!F:F, B27) -> 9 | J27: =I27*G27 -> 4.5
A28: PLOMERIA | B28: ARANDELA PLASTICA 3/4" | C28: EXISTENCIA PREV. 2 | D28: 2.5.8-6723.2 | E28: S/N | F28: 52 | G28: 1.5 | H28: =F28*G28 -> 78 | I28: =F28-SUMIFS(Pedidos!G:G, Pedidos!D:D, C28, Pedidos!E:E, E28, Pedidos!F:F, B28) -> 52 | J28: =I28*G28 -> 78
A29: PLOMERIA | B29: ARO GOMA BASE DE INODORO | C29: 81-0049-OC24 | D29: 2.9.6-5017.22 | E29: 8 | F29: 100 | G29: 1234.2 | H29: =F29*G29 -> 123420 | I29: =F29-SUMIFS(Pedidos!G:G, Pedidos!D:D, C29, Pedidos!E:E, E29, Pedidos!F:F, B29) -> 100 | J29: =I29*G29 -> 123420
A30: PLOMERIA | B30: BOYA OBTURADOR UNIVERSAL REGULABLE PARA DEPOSITO EMBUTIR TIPO IDEAL 1450 | C30: 81-0049-OC24 | D30: 2.9.6-5017.6 | E30: 5 | F30: 50 | G30: 2912.71 | H30: =F30*G30 -> 145635.5 | I30: =F30-SUMIFS(Pedidos!G:G, Pedidos!D:D, C30, Pedidos!E:E, E30, Pedidos!F:F, B30) -> 46 | J30: =I30*G30 -> 133984.66
A31: PLOMERIA | B31: BOYAS FLOTANTE telgopor | C31: EXISTENCIA PREV. 1 | D31: 2.9.6-402.1 | E31: S/N | F31: 5 | G31: 11 | H31: =F31*G31 -> 55 | I31: =F31-SUMIFS(Pedidos!G:G, Pedidos!D:D, C31, Pedidos!E:E, E31, Pedidos!F:F, B31) -> 5 | J31: =I31*G31 -> 55
A32: PLOMERIA | B32: BOYAS FLOTANTE telgopor | C32: EXISTENCIA PREV. 2 | D32: 2.9.6-402.1 | E32: S/N | F32: 14 | G32: 22.02 | H32: =F32*G32 -> 308.28 | I32: =F32-SUMIFS(Pedidos!G:G, Pedidos!D:D, C32, Pedidos!E:E, E32, Pedidos!F:F, B32) -> 14 | J32: =I32*G32 -> 308.28
A33: PLOMERIA | B33: BOTON PULSADO MOCHILA LATERAL | C33: EXISTENCIA PREV. 1 | E33: S/N | F33: 11 | G33: 66 | H33: =F33*G33 -> 726 | I33: =F33-SUMIFS(Pedidos!G:G, Pedidos!D:D, C33, Pedidos!E:E, E33, Pedidos!F:F, B33) -> 11 | J33: =I33*G33 -> 726
A34: PLOMERIA | B34: BOTON PARA MOCHILA CUADRADO PLASTICO | C34: EXISTENCIA PREV. 1 | E34: S/N | F34: 12 | G34: 198 | H34: =F34*G34 -> 2376 | I34: =F34-SUMIFS(Pedidos!G:G, Pedidos!D:D, C34, Pedidos!E:E, E34, Pedidos!F:F, B34) -> 12 | J34: =I34*G34 -> 2376
A35: PLOMERIA | B35: BOTON PULSADOR MOCHILA SUPERIOR REDONDO | C35: EXISTENCIA PREV. 1 | E35: S/N | F35: 9 | G35: 57 | H35: =F35*G35 -> 513 | I35: =F35-SUMIFS(Pedidos!G:G, Pedidos!D:D, C35, Pedidos!E:E, E35, Pedidos!F:F, B35) -> 9 | J35: =I35*G35 -> 513
A36: PLOMERIA | B36: BUJE BRONCE REDUCCION DIAMETRO MAYOR 1/4" | C36: EXISTENCIA PREV. 1 | D36: 2.5.8-3536.11 | E36: S/N | F36: 21 | G36: 0.43 | H36: =F36*G36 -> 9.03 | I36: =F36-SUMIFS(Pedidos!G:G, Pedidos!D:D, C36, Pedidos!E:E, E36, Pedidos!F:F, B36) -> 21 | J36: =I36*G36 -> 9.03
A37: PLOMERIA | B37: BUJE BRONCE REDUCCION DIAMETRO MAYOR 3/8" | C37: EXISTENCIA PREV. 1 | D37: 2.5.8-3536.5 | E37: S/N | F37: 22 | G37: 0.6 | H37: =F37*G37 -> 13.2 | I37: =F37-SUMIFS(Pedidos!G:G, Pedidos!D:D, C37, Pedidos!E:E, E37, Pedidos!F:F, B37) -> 22 | J37: =I37*G37 -> 13.2
A38: PLOMERIA | B38: BUJE BRONCE REDUCCION 1/2" M A 3/8" PESTAÑA | C38: EXISTENCIA PREV. 1 | D38: 2.5.8-3536.5 | E38: S/N | F38: 20 | G38: 0.85 | H38: =F38*G38 -> 17 | I38: =F38-SUMIFS(Pedidos!G:G, Pedidos!D:D, C38, Pedidos!E:E, E38, Pedidos!F:F, B38) -> 20 | J38: =I38*G38 -> 17
A39: PLOMERIA | B39: BUJE HIDROBRONZ REDUCCION 1/2" A 3/8" | C39: EXISTENCIA PREV. 1 | D39: 2.5.8-3536.6 | E39: S/N | F39: 3 | G39: 0.73 | H39: =F39*G39 -> 2.19 | I39: =F39-SUMIFS(Pedidos!G:G, Pedidos!D:D, C39, Pedidos!E:E, E39, Pedidos!F:F, B39) -> 3 | J39: =I39*G39 -> 2.19
A40: PLOMERIA | B40: BUJE HIDROBRONZ REDUCCION 1" A 3/4" | C40: EXISTENCIA PREV. 1 | D40: 2.5.8-3536.4 | E40: S/N | F40: 19 | G40: 1.37 | H40: =F40*G40 -> 26.03 | I40: =F40-SUMIFS(Pedidos!G:G, Pedidos!D:D, C40, Pedidos!E:E, E40, Pedidos!F:F, B40) -> 19 | J40: =I40*G40 -> 26.03
A41: PLOMERIA | B41: CAÑAMO BOLSA X 100 GR | C41: EXISTENCIA PREV. 1 | E41: S/N | F41: 10 | G41: 7.1 | H41: =F41*G41 -> 71 | I41: =F41-SUMIFS(Pedidos!G:G, Pedidos!D:D, C41, Pedidos!E:E, E41, Pedidos!F:F, B41) -> 10 | J41: =I41*G41 -> 71
A42: PLOMERIA | B42: CAÑAMO BOLSA GRANDE | C42: EXISTENCIA PREV. 1 | E42: S/N | F42: 4 | G42: 2.18 | H42: =F42*G42 -> 8.72 | I42: =F42-SUMIFS(Pedidos!G:G, Pedidos!D:D, C42, Pedidos!E:E, E42, Pedidos!F:F, B42) -> 4 | J42: =I42*G42 -> 8.72
A43: PLOMERIA | B43: CAÑAMO BOLSA X 1000 GR | C43: EXISTENCIA PREV. 1 | E43: S/N | F43: 1 | G43: 165 | H43: =F43*G43 -> 165 | I43: =F43-SUMIFS(Pedidos!G:G, Pedidos!D:D, C43, Pedidos!E:E, E43, Pedidos!F:F, B43) -> 1 | J43: =I43*G43 -> 165
A44: PLOMERIA | B44: CAÑO GALVANIZADO 1/2" X 6,40 M | C44: EXISTENCIA PREV. 1 | D44: 2.7.1-6094.96 | E44: S/N | F44: 10 | G44: 13.85 | H44: =F44*G44 -> 138.5 | I44: =F44-SUMIFS(Pedidos!G:G, Pedidos!D:D, C44, Pedidos!E:E, E44, Pedidos!F:F, B44) -> 10 | J44: =I44*G44 -> 138.5
A45: PLOMERIA | B45: CAÑO GALVANIZADO 1/2" X 6,40 M | C45: EXISTENCIA PREV. 2 | D45: 2.7.1-6094.96 | E45: S/N | F45: 10 | G45: 32.67 | H45: =F45*G45 -> 326.7 | I45: =F45-SUMIFS(Pedidos!G:G, Pedidos!D:D, C45, Pedidos!E:E, E45, Pedidos!F:F, B45) -> 10 | J45: =I45*G45 -> 326.7
A46: PLOMERIA | B46: CAÑO GALVANIZADO 3/4" X 6,40 M | C46: EXISTENCIA PREV. 1 | D46: 2.7.1-6094.79 | E46: S/N | F46: 10 | G46: 45.76 | H46: =F46*G46 -> 457.6 | I46: =F46-SUMIFS(Pedidos!G:G, Pedidos!D:D, C46, Pedidos!E:E, E46, Pedidos!F:F, B46) -> 10 | J46: =I46*G46 -> 457.6
A47: PLOMERIA | B47: CAÑO GALVANIZADO 1" X 6,40 M | C47: EXISTENCIA PREV. 1 | D47: 2.7.1-6094.193 | E47: S/N | F47: 5 | G47: 69.27 | H47: =F47*G47 -> 346.35 | I47: =F47-SUMIFS(Pedidos!G:G, Pedidos!D:D, C47, Pedidos!E:E, E47, Pedidos!F:F, B47) -> 5 | J47: =I47*G47 -> 346.35
A48: PLOMERIA | B48: CANO PVC 38/40 X 4 MTS | C48: EXISTENCIA PREV. 1 | D48: 2.5.8-378.64 | E48: S/N | F48: 5 | G48: 34.08 | H48: =F48*G48 -> 170.4 | I48: =F48-SUMIFS(Pedidos!G:G, Pedidos!D:D, C48, Pedidos!E:E, E48, Pedidos!F:F, B48) -> 4 | J48: =I48*G48 -> 136.32
A49: PLOMERIA | B49: CANO PVC 38/40 X 4 MTS | C49: EXISTENCIA PREV. 2 | D49: 2.5.8-378.64 | E49: S/N | F49: 6 | G49: 94.8 | H49: =F49*G49 -> 568.8 | I49: =F49-SUMIFS(Pedidos!G:G, Pedidos!D:D, C49, Pedidos!E:E, E49, Pedidos!F:F, B49) -> 6 | J49: =I49*G49 -> 568.8
A50: PLOMERIA | B50: CAÑO PVC X 3,2 MTS 50 MM | C50: EXISTENCIA PREV. 1 | D50: 2.5.8-378.438 | E50: S/N | F50: 9 | G50: 26.3 | H50: =F50*G50 -> 236.7 | I50: =F50-SUMIFS(Pedidos!G:G, Pedidos!D:D, C50, Pedidos!E:E, E50, Pedidos!F:F, B50) -> 9 | J50: =I50*G50 -> 236.7
A51: PLOMERIA | B51: CAÑO PVC X 4 MTS 60 MM | C51: EXISTENCIA PREV. 1 | D51: 2.5.8-378.222 | E51: S/N | F51: 1 | G51: 159.06 | H51: =F51*G51 -> 159.06 | I51: =F51-SUMIFS(Pedidos!G:G, Pedidos!D:D, C51, Pedidos!E:E, E51, Pedidos!F:F, B51) -> 1 | J51: =I51*G51 -> 159.06
A52: PLOMERIA | B52: CAÑO PVC X 4 MTS 150 MM | C52: EXISTENCIA PREV. 1 | D52: 2.5.8-378.131 | E52: S/N | F52: 6 | G52: 556 | H52: =F52*G52 -> 3336 | I52: =F52-SUMIFS(Pedidos!G:G, Pedidos!D:D, C52, Pedidos!E:E, E52, Pedidos!F:F, B52) -> 6 | J52: =I52*G52 -> 3336
A53: PLOMERIA | B53: Carga De Agua 1/2 PuLG P/mochila Capea O Mónaco | C53: 81-0050-OC24 | D53: 2.9.6-1792.89 | E53: 27 | F53: 50 | G53: 10375 | H53: =F53*G53 -> 518750 | I53: =F53-SUMIFS(Pedidos!G:G, Pedidos!D:D, C53, Pedidos!E:E, E53, Pedidos!F:F, B53) -> 47 | J53: =I53*G53 -> 487625
A54: PLOMERIA | B54: CARTUCHO PARA PRESSMA TIC FV (360 361 362) 0360.25.0 | C54: 81-0052-OC24 | D54: 2.7.9-8857.185 | E54: 17 | F54: 10 | G54: 34200 | H54: =F54*G54 -> 342000 | I54: =F54-SUMIFS(Pedidos!G:G, Pedidos!D:D, C54, Pedidos!E:E, E54, Pedidos!F:F, B54) -> 10 | J54: =I54*G54 -> 342000
A55: PLOMERIA | B55: CANILLA LAVATORIO AUTOMATICA TEMPORIZADA A PRESION TIPO FV; PAZZA; GENEBRE O CALIDAD SUPERIOR. LARGO CANILLA 10 CM (+/- 10%), ALTURA CANILLA 10 CM (+/- 20%) | C55: 81-0054-OC24 | D55: 2.7.9-626.15 | E55: 15 | F55: 20 | G55: 29300 | H55: =F55*G55 -> 586000 | I55: =F55-SUMIFS(Pedidos!G:G, Pedidos!D:D, C55, Pedidos!E:E, E55, Pedidos!F:F, B55) -> 10 | J55: =I55*G55 -> 293000
A56: PLOMERIA | B56: CODO BRONCE M/H 3/8" | C56: EXISTENCIA PREV. 1 | D56: 2.7.9-6383.29 | E56: S/N | F56: 3 | G56: 1.92 | H56: =F56*G56 -> 5.76 | I56: =F56-SUMIFS(Pedidos!G:G, Pedidos!D:D, C56, Pedidos!E:E, E56, Pedidos!F:F, B56) -> 3 | J56: =I56*G56 -> 5.76
A57: PLOMERIA | B57: CODO BRONCE M/M 3/8" | C57: EXISTENCIA PREV. 1 | D57: 2.7.9-6383.29 | E57: S/N | F57: 3 | G57: 2.68 | H57: =F57*G57 -> 8.04 | I57: =F57-SUMIFS(Pedidos!G:G, Pedidos!D:D, C57, Pedidos!E:E, E57, Pedidos!F:F, B57) -> 3 | J57: =I57*G57 -> 8.04
A58: PLOMERIA | B58: CODO BRONCE H/H 3/8" | C58: EXISTENCIA PREV. 1 | D58: 2.7.9-6383.29 | E58: S/N | F58: 2 | G58: 4.19 | H58: =F58*G58 -> 8.38 | I58: =F58-SUMIFS(Pedidos!G:G, Pedidos!D:D, C58, Pedidos!E:E, E58, Pedidos!F:F, B58) -> 2 | J58: =I58*G58 -> 8.38
A59: PLOMERIA | B59: CODO HB M/E 1/2 X 1/2 | C59: EXISTENCIA PREV. 1 | D59: 2.7.9-5844.2 | E59: S/N | F59: 23 | G59: 1.37 | H59: =F59*G59 -> 31.51 | I59: =F59-SUMIFS(Pedidos!G:G, Pedidos!D:D, C59, Pedidos!E:E, E59, Pedidos!F:F, B59) -> 23 | J59: =I59*G59 -> 31.51
A60: PLOMERIA | B60: CODO HB E/E 1/2" | C60: EXISTENCIA PREV. 1 | D60: 2.7.9-5844.2 | E60: S/N | F60: 50 | G60: 1.06 | H60: =F60*G60 -> 53 | I60: =F60-SUMIFS(Pedidos!G:G, Pedidos!D:D, C60, Pedidos!E:E, E60, Pedidos!F:F, B60) -> 50 | J60: =I60*G60 -> 53
A61: PLOMERIA | B61: CODO HB E/E 1/2" | C61: EXISTENCIA PREV. 2 | D61: 2.7.9-5844.2 | E61: S/N | F61: 50 | G61: 1.72 | H61: =F61*G61 -> 86 | I61: =F61-SUMIFS(Pedidos!G:G, Pedidos!D:D, C61, Pedidos!E:E, E61, Pedidos!F:F, B61) -> 50 | J61: =I61*G61 -> 86
A62: PLOMERIA | B62: CODO HB E/E 1/2" | C62: EXISTENCIA PREV. 3 | D62: 2.7.9-5844.2 | E62: S/N | F62: 45 | G62: 0.65 | H62: =F62*G62 -> 29.25 | I62: =F62-SUMIFS(Pedidos!G:G, Pedidos!D:D, C62, Pedidos!E:E, E62, Pedidos!F:F, B62) -> 45 | J62: =I62*G62 -> 29.25
A63: PLOMERIA | B63: CODO HB E/H 3/4" | C63: EXISTENCIA PREV. 1 | D63: 2.7.9-5844.3 | E63: S/N | F63: 145 | G63: 3.74 | H63: =F63*G63 -> 542.3 | I63: =F63-SUMIFS(Pedidos!G:G, Pedidos!D:D, C63, Pedidos!E:E, E63, Pedidos!F:F, B63) -> 145 | J63: =I63*G63 -> 542.3
A64: PLOMERIA | B64: CODO HB E/E 3/4" A 1/2" REDUCCION | C64: EXISTENCIA PREV. 1 | D64: 2.7.9-5844.3 | E64: S/N | F64: 20 | G64: 1.63 | H64: =F64*G64 -> 32.6 | I64: =F64-SUMIFS(Pedidos!G:G, Pedidos!D:D, C64, Pedidos!E:E, E64, Pedidos!F:F, B64) -> 20 | J64: =I64*G64 -> 32.6
A65: PLOMERIA | B65: CODO HB H/H 1" | C65: EXISTENCIA PREV. 1 | D65: 2.7.9-6383.72 | E65: S/N | F65: 29 | G65: 2.76 | H65: =F65*G65 -> 80.04 | I65: =F65-SUMIFS(Pedidos!G:G, Pedidos!D:D, C65, Pedidos!E:E, E65, Pedidos!F:F, B65) -> 29 | J65: =I65*G65 -> 80.04
A66: PLOMERIA | B66: CODO HB H/H 1" | C66: EXISTENCIA PREV. 2 | D66: 2.7.9-6383.72 | E66: S/N | F66: 9 | G66: 2.19 | H66: =F66*G66 -> 19.71 | I66: =F66-SUMIFS(Pedidos!G:G, Pedidos!D:D, C66, Pedidos!E:E, E66, Pedidos!F:F, B66) -> 9 | J66: =I66*G66 -> 19.71
A67: PLOMERIA | B67: CODO GALVANIZADO H/M 1/2" | C67: EXISTENCIA PREV. 1 | D67: 2.7.1-6082.107 | E67: S/N | F67: 12 | G67: 1.09 | H67: =F67*G67 -> 13.08 | I67: =F67-SUMIFS(Pedidos!G:G, Pedidos!D:D, C67, Pedidos!E:E, E67, Pedidos!F:F, B67) -> 12 | J67: =I67*G67 -> 13.08
... A74: PLOMERIA | B74: CODO PVC DIAMETRO 150 MM 90° | C74: EXISTENCIA PREV. 1 | D74: 2.5.8-1147.59 | E74: S/N | F74: 2 | G74: 80.3 | H74: =F74*G74 -> 160.6 | I74: =F74-SUMIFS(Pedidos!G:G, Pedidos!D:D, C74, Pedidos!E:E, E74, Pedidos!F:F, B74) -> 2 | J74: =I74*G74 -> 160.6
A75: PLOMERIA | B75: CONEXIONES P/ SANITARIOS; TIPO FLEXIBLE MALLADO - MATERAIL ACERO INOXIDABLE - GOMA - LONG. DE CUERPO 40 CM - TIPO DE CONEXIÓN 1/2 PULGADAS | C75: 81-0049-OC24 | D75: 2.7.9-1656.16 | E75: 1 | F75: 50 | G75: 3447.06 | H75: =F75*G75 -> 172353 | I75: =F75-SUMIFS(Pedidos!G:G, Pedidos!D:D, C75, Pedidos!E:E, E75, Pedidos!F:F, B75) -> 22 | J75: =I75*G75 -> 75835.32
A76: PLOMERIA | B76: CONEXIONES P/ SANITARIOS; TIPO FLEXIBLE MALLADO - MATERAIL ACERO INOXIDABLE - GOMA - LONG. DE CUERPO 30 CM - TIPO DE CONEXIÓN 1/2 PULGADAS | C76: 81-0049-OC24 | D76: 2.7.9-1656.17 | E76: 2 | F76: 50 | G76: 3292.08 | H76: =F76*G76 -> 164604 | I76: =F76-SUMIFS(Pedidos!G:G, Pedidos!D:D, C76, Pedidos!E:E, E76, Pedidos!F:F, B76) -> 45 | J76: =I76*G76 -> 148143.6
A77: PLOMERIA | B77: CINTAS DESTAPA CAÑERÍAS; MATERIAL: ACERO, LONG. DE CUERPO: 15 M | C77: 81-0050-OC24 | D77: 2.9.9-7839.2 | E77: 3 | F77: 2 | G77: 12076 | H77: =F77*G77 -> 24152 | I77: =F77-SUMIFS(Pedidos!G:G, Pedidos!D:D, C77, Pedidos!E:E, E77, Pedidos!F:F, B77) -> 2 | J77: =I77*G77 -> 24152
A78: PLOMERIA | B78: CINTA DE TEFLÓN X ROLLO, MEDIDA 3/4 X 20 MTS. | C78: 81-0053-OC25 | D78: 2.2.2-1044.47 | E78: 11 | F78: 50 | G78: 1146.44 | H78: =F78*G78 -> 57322 | I78: =F78-SUMIFS(Pedidos!G:G, Pedidos!D:D, C78, Pedidos!E:E, E78, Pedidos!F:F, B78) -> 50 | J78: =I78*G78 -> 57322
A79: PLOMERIA | B79: CINTA DE TEFLÓN X ROLLO, MEDIDA 3/4 X 20 MTS. | C79: EXISTENCIA PREV. 1 | D79: 2.2.2-1044.47 | E79: S/N | F79: 15 | G79: 21.9 | H79: =F79*G79 -> 328.5 | I79: =F79-SUMIFS(Pedidos!G:G, Pedidos!D:D, C79, Pedidos!E:E, E79, Pedidos!F:F, B79) -> 15 | J79: =I79*G79 -> 328.5
A80: PLOMERIA | B80: CINTA DE TEFLÓN X ROLLO, MEDIDA 3/4 X 20 MTS. | C80: EXISTENCIA PREV. 2 | D80: 2.2.2-1044.47 | E80: S/N | F80: 14 | G80: 6.29 | H80: =F80*G80 -> 88.06 | I80: =F80-SUMIFS(Pedidos!G:G, Pedidos!D:D, C80, Pedidos!E:E, E80, Pedidos!F:F, B80) -> 14 | J80: =I80*G80 -> 88.06
A81: PLOMERIA | B81: CONEXIÓN FLEXIBLE PARA MINGITORIO | C81: EXISTENCIA PREV. 1 | E81: S/N | F81: 19 | G81: 340 | H81: =F81*G81 -> 6460 | I81: =F81-SUMIFS(Pedidos!G:G, Pedidos!D:D, C81, Pedidos!E:E, E81, Pedidos!F:F, B81) -> 19 | J81: =I81*G81 -> 6460
A82: PLOMERIA | B82: CUPLA BRONCE 1" PASANTE | C82: EXISTENCIA PREV. 1 | E82: S/N | F82: 7 | G82: 1.7 | H82: =F82*G82 -> 11.9 | I82: =F82-SUMIFS(Pedidos!G:G, Pedidos!D:D, C82, Pedidos!E:E, E82, Pedidos!F:F, B82) -> 7 | J82: =I82*G82 -> 11.9
A83: PLOMERIA | B83: CUPLA BRONCE 3/4" PASANTE | C83: EXISTENCIA PREV. 1 | E83: S/N | F83: 13 | G83: 1.15 | H83: =F83*G83 -> 14.95 | I83: =F83-SUMIFS(Pedidos!G:G, Pedidos!D:D, C83, Pedidos!E:E, E83, Pedidos!F:F, B83) -> 13 | J83: =I83*G83 -> 14.95
A84: PLOMERIA | B84: CUPLA HB 1/2" PASANTE | C84: EXISTENCIA PREV. 1 | E84: S/N | F84: 3 | G84: 0.84 | H84: =F84*G84 -> 2.52 | I84: =F84-SUMIFS(Pedidos!G:G, Pedidos!D:D, C84, Pedidos!E:E, E84, Pedidos!F:F, B84) -> 3 | J84: =I84*G84 -> 2.52
A85: PLOMERIA | B85: CUPLA HB 1/2" PASANTE | C85: EXISTENCIA PREV. 2 | E85: S/N | F85: 30 | G85: 1.82 | H85: =F85*G85 -> 54.6 | I85: =F85-SUMIFS(Pedidos!G:G, Pedidos!D:D, C85, Pedidos!E:E, E85, Pedidos!F:F, B85) -> 30 | J85: =I85*G85 -> 54.6
A86: PLOMERIA | B86: CUPLA HB C/ TOPE 1/2" | C86: EXISTENCIA PREV. 1 | E86: S/N | F86: 20 | G86: 0.84 | H86: =F86*G86 -> 16.8 | I86: =F86-SUMIFS(Pedidos!G:G, Pedidos!D:D, C86, Pedidos!E:E, E86, Pedidos!F:F, B86) -> 20 | J86: =I86*G86 -> 16.8
A87: PLOMERIA | B87: CUPLA HB 3/4" PASANTE | C87: EXISTENCIA PREV. 1 | E87: S/N | F87: 9 | G87: 1.32 | H87: =F87*G87 -> 11.88 | I87: =F87-SUMIFS(Pedidos!G:G, Pedidos!D:D, C87, Pedidos!E:E, E87, Pedidos!F:F, B87) -> 9 | J87: =I87*G87 -> 11.88
A88: PLOMERIA | B88: CUPLA HB 3/4" PASANTE | C88: EXISTENCIA PREV. 2 | E88: S/N | F88: 30 | G88: 2.45 | H88: =F88*G88 -> 73.5 | I88: =F88-SUMIFS(Pedidos!G:G, Pedidos!D:D, C88, Pedidos!E:E, E88, Pedidos!F:F, B88) -> 30 | J88: =I88*G88 -> 73.5
A89: PLOMERIA | B89: CUPLA HB C/ TOPE 3/4" | C89: EXISTENCIA PREV. 1 | E89: S/N | F89: 10 | G89: 0.83 | H89: =F89*G89 -> 8.3 | I89: =F89-SUMIFS(Pedidos!G:G, Pedidos!D:D, C89, Pedidos!E:E, E89, Pedidos!F:F, B89) -> 10 | J89: =I89*G89 -> 8.3
A90: PLOMERIA | B90: CUPLA HB C/ TOPE 3/4" | C90: EXISTENCIA PREV. 2 | E90: S/N | F90: 20 | G90: 1.36 | H90: =F90*G90 -> 27.2 | I90: =F90-SUMIFS(Pedidos!G:G, Pedidos!D:D, C90, Pedidos!E:E, E90, Pedidos!F:F, B90) -> 20 | J90: =I90*G90 -> 27.2
A91: PLOMERIA | B91: CUPLA REDUCCION HB 3/4" A 1/2" | C91: EXISTENCIA PREV. 1 | E91: S/N | F91: 52 | G91: 0.65 | H91: =F91*G91 -> 33.8 | I91: =F91-SUMIFS(Pedidos!G:G, Pedidos!D:D, C91, Pedidos!E:E, E91, Pedidos!F:F, B91) -> 52 | J91: =I91*G91 -> 33.8
A92: PLOMERIA | B92: CUPLA REDUCCION HB 3/4" A 1/2" | C92: EXISTENCIA PREV. 2 | E92: S/N | F92: 20 | G92: 1.32 | H92: =F92*G92 -> 26.4 | I92: =F92-SUMIFS(Pedidos!G:G, Pedidos!D:D, C92, Pedidos!E:E, E92, Pedidos!F:F, B92) -> 20 | J92: =I92*G92 -> 26.4
... A108: PLOMERIA | B108: CURVA PVC DIAMETRO 150 MM 90º | C108: EXISTENCIA PREV. 1 | E108: S/N | F108: 4 | G108: 196 | H108: =F108*G108 -> 784 | I108: =F108-SUMIFS(Pedidos!G:G, Pedidos!D:D, C108, Pedidos!E:E, E108, Pedidos!F:F, B108) -> 4 | J108: =I108*G108 -> 784
A109: PLOMERIA | B109: Descarga Mochila Capea Roca Superior Cromado Repuesto Eco Flush | C109: 81-0052-OC24 | D109: 2.9.6-1792.87 | E109: 31 | F109: 20 | G109: 11650 | H109: =F109*G109 -> 233000 | I109: =F109-SUMIFS(Pedidos!G:G, Pedidos!D:D, C109, Pedidos!E:E, E109, Pedidos!F:F, B109) -> 13 | J109: =I109*G109 -> 151450
A110: PLOMERIA | B110: DEPOSITO P/ MINGITORIO PVC X 8 LTS | C110: EXISTENCIA PREV. 1 | E110: S/N | F110: 5 | G110: 21.9 | H110: =F110*G110 -> 109.5 | I110: =F110-SUMIFS(Pedidos!G:G, Pedidos!D:D, C110, Pedidos!E:E, E110, Pedidos!F:F, B110) -> 5 | J110: =I110*G110 -> 109.5
A111: PLOMERIA | B111: ELECTRODO 2 MM | C111: EXISTENCIA PREV. 1 | E111: S/N | F111: 2878 | G111: 1.36 | H111: =F111*G111 -> 3914.08 | I111: =F111-SUMIFS(Pedidos!G:G, Pedidos!D:D, C111, Pedidos!E:E, E111, Pedidos!F:F, B111) -> 2793 | J111: =I111*G111 -> 3798.48
A112: PLOMERIA | B112: ELECTRODO 2,5 MM | C112: EXISTENCIA PREV. 1 | E112: S/N | F112: 1519 | G112: 1.81 | H112: =F112*G112 -> 2749.39 | I112: =F112-SUMIFS(Pedidos!G:G, Pedidos!D:D, C112, Pedidos!E:E, E112, Pedidos!F:F, B112) -> 1434 | J112: =I112*G112 -> 2595.54
A113: PLOMERIA | B113: ESTERINA EN PANES | C113: EXISTENCIA PREV. 1 | E113: S/N | F113: 52 | G113: 2.2 | H113: =F113*G113 -> 114.4 | I113: =F113-SUMIFS(Pedidos!G:G, Pedidos!D:D, C113, Pedidos!E:E, E113, Pedidos!F:F, B113) -> 52 | J113: =I113*G113 -> 114.4
A114: PLOMERIA | B114: GOMA FUELLE P/ INODORO CORTAS | C114: EXISTENCIA PREV. 1 | E114: S/N | F114: 4 | G114: 31 | H114: =F114*G114 -> 124 | I114: =F114-SUMIFS(Pedidos!G:G, Pedidos!D:D, C114, Pedidos!E:E, E114, Pedidos!F:F, B114) -> 0 | J114: =I114*G114 -> 0
A115: PLOMERIA | B115: GOMA FUELLE PARA INODORO (LARGO) | C115: 81-0049-OC24 | D115: 2.9.6-5017.21 | E115: 7 | F115: 50 | G115: 2262.7 | H115: =F115*G115 -> 113135 | I115: =F115-SUMIFS(Pedidos!G:G, Pedidos!D:D, C115, Pedidos!E:E, E115, Pedidos!F:F, B115) -> 50 | J115: =I115*G115 -> 113135
A116: PLOMERIA | B116: GOMA FUELLE PARA INODORO (LARGO) | C116: EXISTENCIA PREV. 1 | D116: 2.9.6-5017.21 | E116: S/N | F116: 20 | G116: 37 | H116: =F116*G116 -> 740 | I116: =F116-SUMIFS(Pedidos!G:G, Pedidos!D:D, C116, Pedidos!E:E, E116, Pedidos!F:F, B116) -> 16 | J116: =I116*G116 -> 592
A117: PLOMERIA | B117: GOMA RIGIDAS P/INODORO NEGRAS | C117: EXISTENCIA PREV. 1 | E117: S/N | F117: 20 | G117: 2.81 | H117: =F117*G117 -> 56.2 | I117: =F117-SUMIFS(Pedidos!G:G, Pedidos!D:D, C117, Pedidos!E:E, E117, Pedidos!F:F, B117) -> 20 | J117: =I117*G117 -> 56.2
A118: PLOMERIA | B118: GRASA GRAFITADA POTE X 120 GRS | C118: EXISTENCIA PREV. 1 | E118: S/N | F118: 24 | G118: 13.86 | H118: =F118*G118 -> 332.64 | I118: =F118-SUMIFS(Pedidos!G:G, Pedidos!D:D, C118, Pedidos!E:E, E118, Pedidos!F:F, B118) -> 24 | J118: =I118*G118 -> 332.64
A119: PLOMERIA | B119: GRASA GRAFITADA POTE X 120 GRS | C119: EXISTENCIA PREV. 2 | E119: S/N | F119: 10 | G119: 21.3 | H119: =F119*G119 -> 213 | I119: =F119-SUMIFS(Pedidos!G:G, Pedidos!D:D, C119, Pedidos!E:E, E119, Pedidos!F:F, B119) -> 10 | J119: =I119*G119 -> 213
A120: PLOMERIA | B120: GRASA GRAFITADA POTE X 1000 GRS | C120: EXISTENCIA PREV. 1 | E120: S/N | F120: 1 | G120: 186 | H120: =F120*G120 -> 186 | I120: =F120-SUMIFS(Pedidos!G:G, Pedidos!D:D, C120, Pedidos!E:E, E120, Pedidos!F:F, B120) -> 1 | J120: =I120*G120 -> 186
A121: PLOMERIA | B121: KIT O'RING Y RETENES PARA VALVULA DESCARGA INODORO FV 368 (367.17) | C121: 81-0052-OC24 | D121: 2.9.6-1792.11 | E121: 18 | F121: 10 | G121: 11800 | H121: =F121*G121 -> 118000 | I121: =F121-SUMIFS(Pedidos!G:G, Pedidos!D:D, C121, Pedidos!E:E, E121, Pedidos!F:F, B121) -> 9 | J121: =I121*G121 -> 106200
A122: PLOMERIA | B122: LITARGILIO X 250 GRS | C122: EXISTENCIA PREV. 1 | E122: S/N | F122: 24 | G122: 6 | H122: =F122*G122 -> 144 | I122: =F122-SUMIFS(Pedidos!G:G, Pedidos!D:D, C122, Pedidos!E:E, E122, Pedidos!F:F, B122) -> 24 | J122: =I122*G122 -> 144
...

Sheet Pedidos
A1: N° DE PEDIDO | B1: FECHA DE ENTREGA | C1: DEPENDENCIA | D1: ORDEN DE COMPRA | E1: RENGLÓN | F1: BIEN | G1: CANTIDAD ENTREGADA | H1: RUBRO
D2: 81-0080-OC24 | E2: 1 | F2: EQUIPO SPLIT DE 4500 FRIGORÍAS - TIPO DE CLIMATIZACIÓNFRIO/CALOR - EFICIENCIA ENERGÉTICA DE CLASE C O MAYOR | G2: 2
D3: 81-0081-OC24 | E3: 2 | F3: EQUIPO SPLIT DE 6000 FRIGORÍAS - TIPO DE CLIMATIZACIÓN FRIO/CALOR - EFICIENCIA ENERGÉTICA DE CLASE C O MAYOR EN CALEFACCIÓN Y A EN REFRIGERACIÓN - NO CONVERTER | G3: 3
D4: 81-0082-OC24 | E4: 9 | F4: ROLLO DE 2 METROS DE TIRA DE AISLACIÓN TÉRMICA PARA CAÑOS DE 1/2 | G4: 2
D5: 81-0082-OC24 | E5: 10 | F5: ROLLO DE 2 METROS DE TIRA DE AISLACIÓN TÉRMICA PARA CAÑOS DE 1/4 | G5: 4
D6: 81-0082-OC24 | E6: 11 | F6: CINTA DE PVC PARA REFRIGERACIÓN, SIN ADHESIVO – ROLLO DE 20 METROS | G6: 2
D7: 81-0082-OC24 | E7: 13 | F7: MENSULAS PARA AIRE ACONDICIONADO DE 4500 A 6000 FRIGORIAS, 50X50 APROXIMADAMENTE | G7: 1
D8: 81-0082-OC24 | E8: 14 | F8: GARRAFA REFRIGERANTE R410 | G8: 1
D9: 81-0082-OC24 | E9: 15 | F9: GARRAFA REFRIGERANTE R22 | G9: 1
D10: 81-0082-OC24 | E10: 16 | F10: MANGUERA CRISTAL PARA DESAGÜE DE 5/8" – ROLLO DE 50 METROS (PRECIO POR METRO) | G10: 25
D11: 81-0082-OC24 | E11: 17 | F11: TACO DE GOMA, AMORTIGUADOR ANTIVIBRACIÓN – BOLSA X 4 UNIDADES | G11: 1
D12: 81-0082-OC24 | E12: 20 | F12: CAJA DE 200 TORNILLOS TIRAFONDO PARA TARUGO DE 10MM - PRECIO POR UNIDAD | G12: 8
D13: 81-0082-OC24 | E13: 21 | F13: CAJA DE 200 TORNILLOS TIRAFONDO PARA TARUGO DE 8MM | G13: 16
... D77: 81-0059-OC24 | E77: 25 | F77: Conductor tipo taller - 3 x 2,5 mm2 - aislación PVC, normalizado Tipo Pirelli o superior x 100 mts. (PRECIO POR METRO) | G77: 100
D78: EXISTENCIA PREV. 1 | E78: S/N | F78: Panel Plafón Led Embutir 60x60 cm Cuadrado 40w Luz Fría Empotrable | G78: 1
D79: 81-0057-OC24 | E79: 23 | F79: Pinza amperométrica digital Uni-T UT204+ 600ª | G79: 1
D80: EXISTENCIA PREV. 1 | E80: S/N | F80: MODULO TOMA CORRIENTE DE 10 Amp | G80: 16
D81: 81-0058-OC24 | E81: 9 | F81: Módulo 1 toma para embutir - 10 A - Tipo línea Siglo XXI | G81: 16
D82: 81-0058-OC24 | E82: 12 | F82: Módulo punto simple – Tipo Jeluz platinum | G82: 27
D83: 81-0058-OC24 | E83: 11 | F83: Tapa rectangular - Tipo Jeluz platinum | G83: 11
D84: 81-0058-OC24 | E84: 10 | F84: Bastidor rectangular – Tipo Jeluz | G84: 13
D85: 81-0057-OC24 | E85: 3 | F85: Lampara Dicroica Led 7w Gu10 220v Gu 10 - luz fría | G85: 10
D86: 81-0059-OC24 | E86: 25 | F86: Conductor tipo taller - 3 x 2,5 mm2 - aislación PVC, normalizado Tipo Pirelli o superior x 100 mts. (PRECIO POR METRO) | G86: 100
D87: EXISTENCIA PREV. 1 | E87: S/N | F87: SOPORTE LISTON PARA 2 TUBOS | G87: 16
D88: EXISTENCIA PREV. 2 | E88: S/N | F88: SOPORTE LISTON PARA 2 TUBOS | G88: 6
D89: 81-0057-OC24 | E89: 1 | F89: Tubo led 18w T8 220v (reemplazo flurescente 36w) 120 cm - luz fría | G89: 100
D90: 81-0051-OC24 | E90: 32 | F90: Válvula Automática + Tecla De Descarga – Clean- Combo Deca | G90: 4
D91: 81-0058-OC24 | E91: 14 | F91: Zapatilla 4 tomas con cable 2,5 / 3 mts. - con llave de corte (Tipo Kalop, Richi, Cambre o calidad superior) | G91: 11
D92: EXISTENCIA PREV. 1 | E92: S/N | F92: GOMA FUELLE P/ INODORO CORTAS | G92: 2
D93: EXISTENCIA PREV. 1 | E93: S/N | F93: GOMA FUELLE PARA INODORO (LARGO) | G93: 3
D94: 81-0054-OC24 | E94: 26 | F94: TORNILLOS FIX CABEZA FRESADA RANURA PHILLIPS ACABADO ZINCADO AMARILLO 6 X 60 MM | G94: 20
D95: 81-0054-OC24 | E95: 24 | F95: TORNILLOS FIX CABEZA FRESADA RANURA PHILLIPS ACABADO ZINCADO AMARILLO 4 X 35 MM | G95: 40
D96: 81-0050-OC24 | E96: 12 | F96: SELLADOR DE ROSCAS SANITARIAS CAUCHO X 125 CC TIPO HYDRO 3 | G96: 5
D97: 81-0049-OC24 | E97: 1 | F97: CONEXIONES P/ SANITARIOS; TIPO FLEXIBLE MALLADO - MATERAIL ACERO INOXIDABLE - GOMA - LONG. DE CUERPO 40 CM - TIPO DE CONEXIÓN 1/2 PULGADAS | G97: 6
D98: 81-0054-OC24 | E98: 19 | F98: ADHESIVO - CEMENTO DE CONTACTO; TIPO: DE CONTACTO, PRESENTACION: ENVASE X 1 L | G98: 2
D99: 81-0054-OC24 | E99: 15 | F99: CANILLA LAVATORIO AUTOMATICA TEMPORIZADA A PRESION TIPO FV; PAZZA; GENEBRE O CALIDAD SUPERIOR. LARGO CANILLA 10 CM (+/- 10%), ALTURA CANILLA 10 CM (+/- 20%) | G99: 8
D100: 81-0052-OC24 | E100: 31 | F100: Descarga Mochila Capea Roca Superior Cromado Repuesto Eco Flush | G100: 3
D101: 81-0049-OC24 | E101: 5 | F101: BOYA OBTURADOR UNIVERSAL REGULABLE PARA DEPOSITO EMBUTIR TIPO IDEAL 1450 | G101: 2
D102: 81-0047-OC24 | E102: 10 | F102: Diluyente - Envase x 4L | G102: 4
D103: 81-0047-OC24 | E103: 15 | F103: Pincel cerda larga N° 20 | G103: 12
D104: EXISTENCIA PREV. 1 | E104: S/N | F104: CINTA ENMASCARAR X 12 MM | G104: 4
D105: 81-0047-OC24 | E105: 16 | F105: Pincel cerda larga N° 25 | G105: 8
D106: 81-0047-OC24 | E106: 1 | F106: Enduido - Lata x 10L | G106: 4
D107: 81-0047-OC24 | E107: 4 | F107: Látex interior tipo SW7005 - Lata x 20L | G107: 1
D108: 81-0047-OC24 | E108: 6 | F108: Esmalte sintético blanco - Lata x 4L | G108: 6
D109: 81-0047-OC24 | E109: 18 | F109: Rodillo de lana de 22 cm | G109: 11
D110: 81-0047-OC24 | E110: 17 | F110: Pincel cerda larga N° 40 | G110: 3
D111: EXISTENCIA PREV. 1 | E111: S/N | F111: FIBRADO P/TECHO IMPERMEABILIZANTE LATA 20 KG | G111: 1
D112: 81-0082-OC24 | E112: 23 | F112: CAJA DE 200 ARANDELAS PLANAS PARA TARUGOS DE 8MM | G112: 72
D113: 81-0082-OC24 | E113: 22 | F113: CAJA DE 200 ARANDELAS PLANAS PARA TARUGOS DE 10MM | G113: 12
D114: 81-0082-OC24 | E114: 11 | F114: CINTA DE PVC PARA REFRIGERACIÓN, SIN ADHESIVO – ROLLO DE 20 METROS | G114: 6
D115: 81-0082-OC24 | E115: 20 | F115: CAJA DE 200 TORNILLOS TIRAFONDO PARA TARUGO DE 10MM - PRECIO POR UNIDAD | G115: 20
D116: 81-0082-OC24 | E116: 21 | F116: CAJA DE 200 TORNILLOS TIRAFONDO PARA TARUGO DE 8MM | G116: 64
D117: 81-0082-OC24 | E117: 18 | F117: CAJA DE 200 TARUGOS MULTIPROPÓSITOS DE 8MM | G117: 64
D118: 81-0082-OC24 | E118: 19 | F118: CAJA DE 200 TARUGOS MULTIPROPÓSITOS DE 10MM | G118: 20
D119: 81-0082-OC24 | E119: 8 | F119: ROLLO DE 2 METROS DE TIRA DE AISLACIÓN TÉRMICA PARA CAÑOS DE 3/8 | G119: 2
D120: 81-0082-OC24 | E120: 10 | F120: ROLLO DE 2 METROS DE TIRA DE AISLACIÓN TÉRMICA PARA CAÑOS DE 1/4 | G120: 8
D121: 81-0082-OC24 | E121: 9 | F121: ROLLO DE 2 METROS DE TIRA DE AISLACIÓN TÉRMICA PARA CAÑOS DE 1/2 | G121: 6
D122: 81-0082-OC24 | E122: 7 | F122: ROLLO DE 2 METROS DE TIRA DE AISLACIÓN TÉRMICA PARA CAÑOS DE 5/8 | G122: 3
D123: 81-0082-OC24 | E123: 6 | F123: ROLLO DE 15 METROS CAÑO DE COBRE DE 1/4 | G123: 3
... D125: 81-0082-OC24 | E125: 5 | F125: ROLLO DE 15 METROS CAÑO DE COBRE DE 1/2 | G125: 1
D126: EXISTENCIA PREV. 1 | E126: S/N | F126: SWEATER CON LOGO | G126: 8
D127: EXISTENCIA PREV. 1 | E127: S/N | F127: CAMPERA IMPERMEABLE C/CAPUCHA | G127: 7
D128: EXISTENCIA PREV. 1 | E128: S/N | F128: CAMISA BLANCA M/LARGA CON LOGO VIVIENDA | G128: 3
D129: EXISTENCIA PREV. 1 | E129: S/N | F129: CAMPERA CON LOGO MINISTERIO Y VIVIENDA | G129: 1
D130: EXISTENCIA PREV. 1 | E130: S/N | F130: BUZO AZUL C/LOGO MINISTERIO DEL INTERIOR | G130: 1
D131: 81-0018-OC25 | E131: 1 | F131: Papel obra A4 | G131: 53
D132: EXISTENCIA PREV. 1 | E132: S/N | F132: BOLIGRAFO NEGRO | G132: 275
D133: 81-0037-OC24 | E133: 5 | F133: Bolígrafo azul | G133: 291
D134: EXISTENCIA PREV. 1 | E134: S/N | F134: LAPIZ 2HB | G134: 127
D135: 81-0038-OC24 | E135: 28 | F135: Resaltadores color verde | G135: 32
D136: 81-0038-OC24 | E136: 27 | F136: Resaltadores color amarillo | G136: 35
D137: 81-0038-OC24 | E137: 29 | F137: Resaltadores color naranja | G137: 65
D138: EXISTENCIA PREV. 1 | E138: S/N | F138: GOMA BORRA TINTA Y LAPIZ | G138: 60
D139: 81-0037-OC24 | E139: 32 | F139: Sacapuntas | G139: 24
D140: EXISTENCIA PREV. 1 | E140: S/N | F140: CORRECTOR EN LAPIZ | G140: 445
D141: 81-0037-OC24 | E141: 33 | F141: Tacos de colores 9 x 9 | G141: 27
D142: 81-0041-OC24 | E142: 18 | F142: Folio A4 paquete x 100 unidades | G142: 1710
D143: 81-0038-OC24 | E143: 31 | F143: Resaltadores color celeste | G143: 70
D144: EXISTENCIA PREV. 1 | E144: S/N | F144: TIJERAS CHICA | G144: 36
D145: EXISTENCIA PREV. 1 | E145: S/N | F145: Broches P/abrochadora 10 | G145: 43
D146: 81-0038-OC24 | E146: 30 | F146: Resaltadores color rosa | G146: 77
D147: EXISTENCIA PREV. 1 | E147: S/N | F147: MARCADOR TRAZO FINO AZUL | G147: 30
D148: EXISTENCIA PREV. 1 | E148: S/N | F148: Marcador al agua verde | G148: 7
D149: EXISTENCIA PREV. 1 | E149: S/N | F149: Bolígrafo rojo | G149: 84
D150: EXISTENCIA PREV. 1 | E150: S/N | F150: Cinta para embalar Transparente 5 cm x 50 mts | G150: 52
D151: EXISTENCIA PREV. 1 | E151: S/N | F151: BOLIGRAFO VERDE | G151: 70
D152: EXISTENCIA PREV. 1 | E152: S/N | F152: ADHESIVO TRANSPARENTE X50 ML | G152: 17
D153: EXISTENCIA PREV. 1 | E153: S/N | F153: ADHESIVO BARRA | G153: 11
D154: EXISTENCIA PREV. 1 | E154: S/N | F154: PAPEL OBRA OFICIO | G154: 39
D155: EXISTENCIA PREV. 1 | E155: S/N | F155: MARCADOR PIZARRA ROJO | G155: 14
D156: EXISTENCIA PREV. 1 | E156: S/N | F156: ADHESIVO VINILICO X 250 CC | G156: 12
D157: EXISTENCIA PREV. 1 | E157: S/N | F157: ADHESIVO VINILICO X 30 ML | G157: 27
D158: EXISTENCIA PREV. 1 | E158: S/N | F158: FOLIOS OFICIO | G158: 425
... D164: EXISTENCIA PREV. 1 | E164: S/N | F164: MARCADOR VERDE AL SOLVENTE | G164: 8
D165: 81-0038-OC24 | E165: 14 | F165: Cuaderno tapa dura rayado x 50 hojas | G165: 37
D166: EXISTENCIA PREV. 1 | E166: S/N | F166: ABROCHADORA 10/50 pinza | G166: 4
D167: EXISTENCIA PREV. 1 | E167: S/N | F167: PORTA CINTA CHICO | G167: 4
D168: 81-0038-OC24 | E168: 13 | F168: Clips N° 3 | G168: 5
D169: EXISTENCIA PREV. 1 | E169: S/N | F169: Cúter | G169: 21
...

Sheet Consolidado
A1: CONSOLIDADO DE STOCK Y SALDO
A2: ORDEN DE COMPRA | B2: (Varios elementos)
A3: PRECIO TOTAL | B3: 11792300 | E3: ORDEN DE COMPRA | F3: (Varios elementos)
B5: SUM of PRECIO TOTAL | E5: ABROCHADORA 10/50 pinza | F5: SUM of CANTIDAD COMPRADA | G5: 67
A6: EQUIPO SPLIT DE 4500 FRIGORÍAS - TIPO DE CLIMATIZACIÓNFRIO/CALOR - EFICIENCIA ENERGÉTICA DE CLASE C O MAYOR | B6: 11792300 | F6: SUM of BIENES EN STOCK | G6: 58
A7: Total general | B7: 11792300 | E7: ABROCHADORA 21/6 pinza | F7: SUM of CANTIDAD COMPRADA | G7: 64
F8: SUM of BIENES EN STOCK | G8: 59
E9: ABROCHADORA ESCRITORIO 64 | F9: SUM of CANTIDAD COMPRADA | G9: 74
F10: SUM of BIENES EN STOCK | G10: 60
E11: ABROCHADORA N°23 pinza | F11: SUM of CANTIDAD COMPRADA | G11: 4
F12: SUM of BIENES EN STOCK | G12: 4
E13: ACOPLE RECTO 10 X 20 | F13: SUM of CANTIDAD COMPRADA | G13: 96
F14: SUM of BIENES EN STOCK | G14: 96
E15: ACOPLE RECTO 40 X 16 | F15: SUM of CANTIDAD COMPRADA | G15: 93
F16: SUM of BIENES EN STOCK | G16: 93
E17: ADAPTADOR DE 2 REDONDO A 2 PLANO | F17: SUM of CANTIDAD COMPRADA | G17: 15
F18: SUM of BIENES EN STOCK | G18: 15
E19: ADAPTADOR DE 3 PLANO A 2 REDONDO | F19: SUM of CANTIDAD COMPRADA | G19: 29
F20: SUM of BIENES EN STOCK | G20: 29
E21: ADHESIVO - CEMENTO DE CONTACTO; TIPO: DE CONTACTO, PRESENTACION: ENVASE X 1 L | F21: SUM of CANTIDAD COMPRADA | G21: 10
F22: SUM of BIENES EN STOCK | G22: 6
E23: ADHESIVO BARRA | F23: SUM of CANTIDAD COMPRADA | G23: 325
F24: SUM of BIENES EN STOCK | G24: 304
E25: ADHESIVO COLA CARPINTERO BLANCO | F25: SUM of CANTIDAD COMPRADA | G25: 1
F26: SUM of BIENES EN STOCK | G26: 1
E27: Adhesivo tipo boligoma x 30 ml. | F27: SUM of CANTIDAD COMPRADA | G27: 100
F28: SUM of BIENES EN STOCK | G28: 100
E29: ADHESIVO TRANSPARENTE X50 ML | F29: SUM of CANTIDAD COMPRADA | G29: 94
F30: SUM of BIENES EN STOCK | G30: 70
E31: ADHESIVO VINILICO X 250 CC | F31: SUM of CANTIDAD COMPRADA | G31: 117
F32: SUM of BIENES EN STOCK | G32: 94
E33: ADHESIVO VINILICO X 30 ML | F33: SUM of CANTIDAD COMPRADA | G33: 281
F34: SUM of BIENES EN STOCK | G34: 238
E35: ALMOHADILLA PARA SELLOS | F35: SUM of CANTIDAD COMPRADA | G35: 41
F36: SUM of BIENES EN STOCK | G36: 41
E37: AMOLADORA ANGULAR DE BANCO 150 MM 250 WATTS | F37: SUM of CANTIDAD COMPRADA | G37: 2
F38: SUM of BIENES EN STOCK | G38: 2
E39: ARANDELA PLASTICA 1/2" | F39: SUM of CANTIDAD COMPRADA | G39: 27
F40: SUM of BIENES EN STOCK | G40: 27
E41: ARANDELA PLASTICA 3/4" | F41: SUM of CANTIDAD COMPRADA | G41: 61
F42: SUM of BIENES EN STOCK | G42: 61
E43: ARANDELAS DE CARTON | F43: SUM of CANTIDAD COMPRADA | G43: 53
F44: SUM of BIENES EN STOCK | G44: 53
E45: ARCHIVOS PLASTICOS | F45: SUM of CANTIDAD COMPRADA | G45: 423
F46: SUM of BIENES EN STOCK | G46: 330
E47: ARO GOMA BASE DE INODORO | F47: SUM of CANTIDAD COMPRADA | G47: 100
F48: SUM of BIENES EN STOCK | G48: 100
E49: Bandas elásticas grandes | F49: SUM of CANTIDAD COMPRADA | G49: 100
F50: SUM of BIENES EN STOCK | G50: 67
E51: BANDEJA PORTA CABLE | F51: SUM of CANTIDAD COMPRADA | G51: 2
F52: SUM of BIENES EN STOCK | G52: 2
E53: BARBIJOS | F53: SUM of CANTIDAD COMPRADA | G53: 8
F54: SUM of BIENES EN STOCK | G54: 8
E55: Bastidor rectangular – Tipo Jeluz | F55: SUM of CANTIDAD COMPRADA | G55: 300
F56: SUM of BIENES EN STOCK | G56: 189
E57: BASTIDORES DE CHAPA | F57: SUM of CANTIDAD COMPRADA | G57: 153
F58: SUM of BIENES EN STOCK | G58: 153
E59: BATERIAS RECARG. GEL P/EQUIPO ALARMA | F59: SUM of CANTIDAD COMPRADA | G59: 90
F60: SUM of BIENES EN STOCK | G60: 90
E61: Bibliorato tamaño carta | F61: SUM of CANTIDAD COMPRADA | G61: 100
F62: SUM of BIENES EN STOCK | G62: 76
E63: Bibliorato tamaño oficio | F63: SUM of CANTIDAD COMPRADA | G63: 100
F64: SUM of BIENES EN STOCK | G64: 76
E65: Bolígrafo azul | F65: SUM of CANTIDAD COMPRADA | G65: 1000
F66: SUM of BIENES EN STOCK | G66: 330
E67: BOLIGRAFO NEGRO | F67: SUM of CANTIDAD COMPRADA | G67: 1569
F68: SUM of BIENES EN STOCK | G68: 1160
E69: Bolígrafo rojo | F69: SUM of CANTIDAD COMPRADA | G69: 998
F70: SUM of BIENES EN STOCK | G70: 884
E71: BOLIGRAFO VERDE | F71: SUM of CANTIDAD COMPRADA | G71: 1179
F72: SUM of BIENES EN STOCK | G72: 1099
E73: BORCEGUI SUELA GOMA CAÑA LARGA | F73: SUM of CANTIDAD COMPRADA | G73: 18
F74: SUM of BIENES EN STOCK | G74: 18
E75: BOTON PARA MOCHILA CUADRADO PLASTICO | F75: SUM of CANTIDAD COMPRADA | G75: 12
F76: SUM of BIENES EN STOCK | G76: 12
E77: BOTON PULSADO MOCHILA LATERAL | F77: SUM of CANTIDAD COMPRADA | G77: 11
F78: SUM of BIENES EN STOCK | G78: 11
E79: BOTON PULSADOR MOCHILA SUPERIOR REDONDO | F79: SUM of CANTIDAD COMPRADA | G79: 9
F80: SUM of BIENES EN STOCK | G80: 9
E81: BOYA OBTURADOR UNIVERSAL REGULABLE PARA DEPOSITO EMBUTIR TIPO IDEAL 1450 | F81: SUM of CANTIDAD COMPRADA | G81: 50
F82: SUM of BIENES EN STOCK | G82: 46
E83: BOYAS FLOTANTE telgopor | F83: SUM of CANTIDAD COMPRADA | G83: 19
F84: SUM of BIENES EN STOCK | G84: 19
E85: BROCHE APRIETA PAPEL 25 mm | F85: SUM of CANTIDAD COMPRADA | G85: 1193
F86: SUM of BIENES EN STOCK | G86: 1193
E87: BROCHE APRIETA PAPEL 41 mm | F87: SUM of CANTIDAD COMPRADA | G87: 1176
F88: SUM of BIENES EN STOCK | G88: 1176
E89: BROCHE DORADO N° 14 | F89: SUM of CANTIDAD COMPRADA | G89: 15
F90: SUM of BIENES EN STOCK | G90: 15
E91: BROCHE DORADO N° 4 | F91: SUM of CANTIDAD COMPRADA | G91: 20
F92: SUM of BIENES EN STOCK | G92: 20
E93: BROCHE DORADO Nº 12 | F93: SUM of CANTIDAD COMPRADA | G93: 105
F94: SUM of BIENES EN STOCK | G94: 105
E95: BROCHE DORADO Nº 8 | F95: SUM of CANTIDAD COMPRADA | G95: 116
F96: SUM of BIENES EN STOCK | G96: 116
E97: BROCHE P/ABROCHADORA 21/6 | F97: SUM of CANTIDAD COMPRADA | G97: 808
F98: SUM of BIENES EN STOCK | G98: 759
E99: BROCHE P/ABROCHADORA 64 | F99: SUM of CANTIDAD COMPRADA | G99: 771
F100: SUM of BIENES EN STOCK | G100: 706
E101: BROCHE P/ABROCHADORA N° 23/10 23/24 | F101: SUM of CANTIDAD COMPRADA | G101: 20
...

Sheet CIERRE POR RUBRO
C3: SUM of BIENES EN STOCK
A4: CABLE CANAL | C4: 791
A5: ELECTRICIDAD | C5: 30697
A6: INSUMOS AIRES | C6: 7422
A7: LIBRERIA | C7: 123957
A8: PINTURA | C8: 2879
A9: PLOMERIA | C9: 12311
A10: TERMOFUSION | C10: 869
A11: VARIOS | C11: 37
A12: VESTIMENTA | C12: 1017
A13: Total general | C13: 179980
